{
  "last_update": "2026-05-21T08:25:56.384815+00:00",
  "site": "Istituto Comprensivo via Moisè Loria",
  "circulars_url": "https://www.icsmoiseloria.edu.it/pvw2/app/default/index.php?cerca=primaria&categoria=0&tipo=comunicati&storico=on",
  "news_url": "https://www.icsmoiseloria.edu.it/archivio-news",
  "circular": {
    "id": "https://web.spaggiari.eu/sdg2/Documenti/BachecaCvv/MIME0288/9855085?download=1",
    "type": "circular",
    "title": "PRIMARIA SECONDARIA ALUNNI CIRCOLARE N.34-Primo giugno",
    "circular_date": "20/05/2026",
    "published_date": "20/05/2026",
    "tipologia": "Tutto il personale, Riservata",
    "attachment_name": "PRIMARIA SECONDARIA CIRC_34_Primo giugno.pdf",
    "link": "https://web.spaggiari.eu/sdg2/Documenti/BachecaCvv/MIME0288/9855085?download=1",
    "source_url": "https://www.icsmoiseloria.edu.it/pvw2/app/default/index.php?cerca=primaria&categoria=0&tipo=comunicati&storico=on"
  },
  "news": [
    {
      "id": "https://www.icsmoiseloria.edu.it/pagine/saggio-di-flauto",
      "type": "news",
      "title": "Momento musicale al flauto dolce",
      "date": "",
      "link": "https://www.icsmoiseloria.edu.it/pagine/saggio-di-flauto",
      "source_url": "https://www.icsmoiseloria.edu.it/archivio-news"
    },
    {
      "id": "https://www.icsmoiseloria.edu.it/pagine/progetto-educazione-alla-legalit",
      "type": "news",
      "title": "Progetto \"Educazione alla Legalità\"",
      "date": "",
      "link": "https://www.icsmoiseloria.edu.it/pagine/progetto-educazione-alla-legalit",
      "source_url": "https://www.icsmoiseloria.edu.it/archivio-news"
    },
    {
      "id": "https://www.icsmoiseloria.edu.it/pagine/giornata-sportiva---secondaria-carlo-porta-1",
      "type": "news",
      "title": "Giornata Sportiva - Secondaria Carlo Porta",
      "date": "",
      "link": "https://www.icsmoiseloria.edu.it/pagine/giornata-sportiva---secondaria-carlo-porta-1",
      "source_url": "https://www.icsmoiseloria.edu.it/archivio-news"
    },
    {
      "id": "https://www.icsmoiseloria.edu.it/pagine/saggio-finale-delle-classi-a-indirizzo-musicale",
      "type": "news",
      "title": "Saggio finale delle classi a indirizzo musicale",
      "date": "",
      "link": "https://www.icsmoiseloria.edu.it/pagine/saggio-finale-delle-classi-a-indirizzo-musicale",
      "source_url": "https://www.icsmoiseloria.edu.it/archivio-news"
    },
    {
      "id": "https://www.icsmoiseloria.edu.it/pagine/io-sono-laltro-agenda-2030---classe-vb---primaria-foppette",
      "type": "news",
      "title": "\"Io sono l'altro: agenda 2030\" - classe VB - Primaria Foppette",
      "date": "",
      "link": "https://www.icsmoiseloria.edu.it/pagine/io-sono-laltro-agenda-2030---classe-vb---primaria-foppette",
      "source_url": "https://www.icsmoiseloria.edu.it/archivio-news"
    },
    {
      "id": "https://www.icsmoiseloria.edu.it/pagine/perfezionamento-iscrizione-classi-prime-as-20262027",
      "type": "news",
      "title": "Perfezionamento iscrizione classi prime A.S. 2026/2027",
      "date": "",
      "link": "https://www.icsmoiseloria.edu.it/pagine/perfezionamento-iscrizione-classi-prime-as-20262027",
      "source_url": "https://www.icsmoiseloria.edu.it/archivio-news"
    },
    {
      "id": "https://www.icsmoiseloria.edu.it/pagine/carlo-porta-web-radio---nuova-puntata--",
      "type": "news",
      "title": "Carlo Porta Web Radio - Nuova puntata!",
      "date": "",
      "link": "https://www.icsmoiseloria.edu.it/pagine/carlo-porta-web-radio---nuova-puntata--",
      "source_url": "https://www.icsmoiseloria.edu.it/archivio-news"
    },
    {
      "id": "https://www.icsmoiseloria.edu.it/pagine/carlo-porta-web-radio---nuova-puntata--7",
      "type": "news",
      "title": "Carlo Porta Web Radio - Nuova puntata!",
      "date": "",
      "link": "https://www.icsmoiseloria.edu.it/pagine/carlo-porta-web-radio---nuova-puntata--7",
      "source_url": "https://www.icsmoiseloria.edu.it/archivio-news"
    },
    {
      "id": "https://www.icsmoiseloria.edu.it/pagine/carlo-porta-web-radio---nuova-puntata-2",
      "type": "news",
      "title": "Carlo Porta Web Radio - Nuova puntata!",
      "date": "",
      "link": "https://www.icsmoiseloria.edu.it/pagine/carlo-porta-web-radio---nuova-puntata-2",
      "source_url": "https://www.icsmoiseloria.edu.it/archivio-news"
    },
    {
      "id": "https://www.icsmoiseloria.edu.it/pagine/festa-dei-sapori---cina",
      "type": "news",
      "title": "FESTA DEI SAPORI - CINA",
      "date": "",
      "link": "https://www.icsmoiseloria.edu.it/pagine/festa-dei-sapori---cina",
      "source_url": "https://www.icsmoiseloria.edu.it/archivio-news"
    }
  ],
  "external_sources": {
    "comune_milano": {
      "url": "https://www.comune.milano.it/servizi/scuola/pre-scuola-e-giochi-serali-scuole-primarie",
      "title": "Pre-scuola e giochi serali - Scuole primarie",
      "status": "ok",
      "last_state": {
        "id": "11e87a777b5c9d6a66a45f24ce4517e29decde2fcd7c2cc91042cecbb8fabd71",
        "type": "external_page",
        "source": "Comune di Milano",
        "title": "Pre-scuola e giochi serali - Scuole primarie",
        "url": "https://www.comune.milano.it/servizi/scuola/pre-scuola-e-giochi-serali-scuole-primarie",
        "hash": "11e87a777b5c9d6a66a45f24ce4517e29decde2fcd7c2cc91042cecbb8fabd71",
        "checked_at": "2026-05-21T08:25:56.384475+00:00",
        "preview": "Selezione lingua: lingua selezionata العربية 中文 Français 日本語 Ελληνικά English Italiano Русский Español Deutsch Segnalazioni al Fascicolo del Cittadino Barra di ricerca Nascondi navigazione Servizi Notizie Amministrazione Argomenti Ambiente e Animali Anagrafe Casa Cultura Edilizia Giovani Impresa Lavoro e Formazione Milano accessibile Mobilità Partecipazione civica Patrimonio immobiliare Polizia locale e sicurezza Rigenerazione urbana Scuola Servizi funebri Sport Statistica Tributi Volontariato Welfare Ricerca Barra di ricerca Home / Servizi / Scuola / Pre-scuola e giochi serali scuole primarie Pre-scuola e giochi serali scuole primarie Iscrizione Rivolti alle alunne e agli alunni delle scuol"
      },
      "last_error": null
    }
  }
}